{
  "version": "STX Module Performance v1",
  "updated_at": "2026-06-03T11:22:35.683348+00:00",
  "count": 30,
  "items": [
    {
      "key": "ai_pool:1513:100:184.5",
      "module": "ai_pool",
      "reason": "api_ai_pool",
      "created_at": "2026-06-03T06:05:54.507745+00:00",
      "updated_at": "2026-06-03T11:22:17.988022+00:00",
      "status": "closed",
      "code": "1513",
      "name": "中興電",
      "sector": "重電",
      "entry_price": 184.5,
      "last_price": 184.5,
      "best_price": 184.5,
      "worst_price": 184.5,
      "score": 100,
      "change_rate_at_signal": 9.82,
      "volume_ratio_at_signal": 5.28,
      "alert": null,
      "results": {
        "latest_pct": 0.0,
        "max_gain": 0.0,
        "max_drawdown": 0.0,
        "pct_5m": 0.0,
        "pct_10m": 0.0,
        "pct_30m": 0.0,
        "pct_close_proxy": 0.0
      },
      "age_minutes": 316.39
    },
    {
      "key": "ai_pool:1514:100:136.0",
      "module": "ai_pool",
      "reason": "api_ai_pool",
      "created_at": "2026-06-03T06:05:54.507777+00:00",
      "updated_at": "2026-06-03T11:22:19.699947+00:00",
      "status": "closed",
      "code": "1514",
      "name": "亞力",
      "sector": "重電",
      "entry_price": 136.0,
      "last_price": 136.0,
      "best_price": 136.0,
      "worst_price": 136.0,
      "score": 100,
      "change_rate_at_signal": 9.67,
      "volume_ratio_at_signal": 4.86,
      "alert": null,
      "results": {
        "latest_pct": 0.0,
        "max_gain": 0.0,
        "max_drawdown": 0.0,
        "pct_5m": 0.0,
        "pct_10m": 0.0,
        "pct_30m": 0.0,
        "pct_close_proxy": 0.0
      },
      "age_minutes": 316.42
    },
    {
      "key": "ai_pool:1609:100:42.15",
      "module": "ai_pool",
      "reason": "api_ai_pool",
      "created_at": "2026-06-03T06:05:54.507791+00:00",
      "updated_at": "2026-06-03T11:22:21.367481+00:00",
      "status": "closed",
      "code": "1609",
      "name": "大亞",
      "sector": "電線電纜",
      "entry_price": 42.15,
      "last_price": 42.15,
      "best_price": 42.15,
      "worst_price": 42.15,
      "score": 100,
      "change_rate_at_signal": 9.9,
      "volume_ratio_at_signal": 2.94,
      "alert": null,
      "results": {
        "latest_pct": 0.0,
        "max_gain": 0.0,
        "max_drawdown": 0.0,
        "pct_5m": 0.0,
        "pct_10m": 0.0,
        "pct_30m": 0.0,
        "pct_close_proxy": 0.0
      },
      "age_minutes": 316.45
    },
    {
      "key": "ai_pool:1605:95:42.7",
      "module": "ai_pool",
      "reason": "api_ai_pool",
      "created_at": "2026-06-03T06:05:54.507801+00:00",
      "updated_at": "2026-06-03T11:22:23.195173+00:00",
      "status": "closed",
      "code": "1605",
      "name": "華新",
      "sector": "電線電纜",
      "entry_price": 42.7,
      "last_price": 42.7,
      "best_price": 42.7,
      "worst_price": 42.7,
      "score": 95,
      "change_rate_at_signal": 5.56,
      "volume_ratio_at_signal": 1.81,
      "alert": null,
      "results": {
        "latest_pct": 0.0,
        "max_gain": 0.0,
        "max_drawdown": 0.0,
        "pct_5m": 0.0,
        "pct_10m": 0.0,
        "pct_30m": 0.0,
        "pct_close_proxy": 0.0
      },
      "age_minutes": 316.48
    },
    {
      "key": "ai_pool:3324:94:1280.0",
      "module": "ai_pool",
      "reason": "api_ai_pool",
      "created_at": "2026-06-03T06:05:54.507811+00:00",
      "updated_at": "2026-06-03T11:22:24.835763+00:00",
      "status": "closed",
      "code": "3324",
      "name": "雙鴻",
      "sector": "AI散熱",
      "entry_price": 1280.0,
      "last_price": 1280.0,
      "best_price": 1280.0,
      "worst_price": 1280.0,
      "score": 94,
      "change_rate_at_signal": 9.87,
      "volume_ratio_at_signal": 1.26,
      "alert": null,
      "results": {
        "latest_pct": 0.0,
        "max_gain": 0.0,
        "max_drawdown": 0.0,
        "pct_5m": 0.0,
        "pct_10m": 0.0,
        "pct_30m": 0.0,
        "pct_close_proxy": 0.0
      },
      "age_minutes": 316.51
    },
    {
      "key": "ai_pool:8046:94:904.0",
      "module": "ai_pool",
      "reason": "api_ai_pool",
      "created_at": "2026-06-03T06:05:54.507840+00:00",
      "updated_at": "2026-06-03T11:22:26.684866+00:00",
      "status": "closed",
      "code": "8046",
      "name": "南電",
      "sector": "半導體",
      "entry_price": 904.0,
      "last_price": 904.0,
      "best_price": 904.0,
      "worst_price": 904.0,
      "score": 94,
      "change_rate_at_signal": 4.87,
      "volume_ratio_at_signal": 1.22,
      "alert": null,
      "results": {
        "latest_pct": 0.0,
        "max_gain": 0.0,
        "max_drawdown": 0.0,
        "pct_5m": 0.0,
        "pct_10m": 0.0,
        "pct_30m": 0.0,
        "pct_close_proxy": 0.0
      },
      "age_minutes": 316.54
    },
    {
      "key": "ai_pool:2409:94:28.75",
      "module": "ai_pool",
      "reason": "api_ai_pool",
      "created_at": "2026-06-03T06:05:54.507850+00:00",
      "updated_at": "2026-06-03T11:22:29.360870+00:00",
      "status": "closed",
      "code": "2409",
      "name": "友達",
      "sector": "面板",
      "entry_price": 28.75,
      "last_price": 28.75,
      "best_price": 28.75,
      "worst_price": 28.75,
      "score": 94,
      "change_rate_at_signal": 9.94,
      "volume_ratio_at_signal": 0.98,
      "alert": null,
      "results": {
        "latest_pct": 0.0,
        "max_gain": 0.0,
        "max_drawdown": 0.0,
        "pct_5m": 0.0,
        "pct_10m": 0.0,
        "pct_30m": 0.0,
        "pct_close_proxy": 0.0
      },
      "age_minutes": 316.58
    },
    {
      "key": "ai_pool:2317:92:309.0",
      "module": "ai_pool",
      "reason": "api_ai_pool",
      "created_at": "2026-06-03T06:05:54.507859+00:00",
      "updated_at": "2026-06-03T11:22:31.277479+00:00",
      "status": "closed",
      "code": "2317",
      "name": "鴻海",
      "sector": "AI伺服器",
      "entry_price": 309.0,
      "last_price": 309.0,
      "best_price": 309.0,
      "worst_price": 309.0,
      "score": 92,
      "change_rate_at_signal": 2.48,
      "volume_ratio_at_signal": 1.32,
      "alert": null,
      "results": {
        "latest_pct": 0.0,
        "max_gain": 0.0,
        "max_drawdown": 0.0,
        "pct_5m": 0.0,
        "pct_10m": 0.0,
        "pct_30m": 0.0,
        "pct_close_proxy": 0.0
      },
      "age_minutes": 316.61
    },
    {
      "key": "ai_pool:2324:92:47.05",
      "module": "ai_pool",
      "reason": "api_ai_pool",
      "created_at": "2026-06-03T06:05:54.507868+00:00",
      "updated_at": "2026-06-03T11:22:32.942812+00:00",
      "status": "closed",
      "code": "2324",
      "name": "仁寶",
      "sector": "電腦週邊",
      "entry_price": 47.05,
      "last_price": 47.05,
      "best_price": 47.05,
      "worst_price": 47.05,
      "score": 92,
      "change_rate_at_signal": 6.08,
      "volume_ratio_at_signal": 2.24,
      "alert": null,
      "results": {
        "latest_pct": 0.0,
        "max_gain": 0.0,
        "max_drawdown": 0.0,
        "pct_5m": 0.0,
        "pct_10m": 0.0,
        "pct_30m": 0.0,
        "pct_close_proxy": 0.0
      },
      "age_minutes": 316.64
    },
    {
      "key": "ai_pool:3481:86:59.4",
      "module": "ai_pool",
      "reason": "api_ai_pool",
      "created_at": "2026-06-03T06:05:54.507878+00:00",
      "updated_at": "2026-06-03T11:22:34.621974+00:00",
      "status": "closed",
      "code": "3481",
      "name": "群創",
      "sector": "面板",
      "entry_price": 59.4,
      "last_price": 59.4,
      "best_price": 59.4,
      "worst_price": 59.4,
      "score": 86,
      "change_rate_at_signal": 5.69,
      "volume_ratio_at_signal": 0.81,
      "alert": null,
      "results": {
        "latest_pct": 0.0,
        "max_gain": 0.0,
        "max_drawdown": 0.0,
        "pct_5m": 0.0,
        "pct_10m": 0.0,
        "pct_30m": 0.0,
        "pct_close_proxy": 0.0
      },
      "age_minutes": 316.67
    },
    {
      "key": "ai_pool:2376:79:399.0",
      "module": "ai_pool",
      "reason": "api_ai_pool",
      "created_at": "2026-06-03T06:05:54.507886+00:00",
      "updated_at": "2026-06-03T06:06:44.694174+00:00",
      "status": "open",
      "code": "2376",
      "name": "技嘉",
      "sector": "電腦週邊",
      "entry_price": 399.0,
      "last_price": 399.0,
      "best_price": 399.0,
      "worst_price": 399.0,
      "score": 79,
      "change_rate_at_signal": 2.17,
      "volume_ratio_at_signal": 0.91,
      "alert": null,
      "results": {
        "latest_pct": 0.0,
        "max_gain": 0.0,
        "max_drawdown": 0.0
      },
      "age_minutes": 0.84
    },
    {
      "key": "ai_pool:2308:76:2455.0",
      "module": "ai_pool",
      "reason": "api_ai_pool",
      "created_at": "2026-06-03T06:05:54.507895+00:00",
      "updated_at": "2026-06-03T06:06:46.354526+00:00",
      "status": "open",
      "code": "2308",
      "name": "台達電",
      "sector": "重電",
      "entry_price": 2455.0,
      "last_price": 2455.0,
      "best_price": 2455.0,
      "worst_price": 2455.0,
      "score": 76,
      "change_rate_at_signal": 4.02,
      "volume_ratio_at_signal": 0.87,
      "alert": null,
      "results": {
        "latest_pct": 0.0,
        "max_gain": 0.0,
        "max_drawdown": 0.0
      },
      "age_minutes": 0.86
    },
    {
      "key": "ai_pool:3037:73:1000.0",
      "module": "ai_pool",
      "reason": "api_ai_pool",
      "created_at": "2026-06-03T06:05:54.507904+00:00",
      "updated_at": "2026-06-03T06:06:48.088778+00:00",
      "status": "open",
      "code": "3037",
      "name": "欣興",
      "sector": "半導體",
      "entry_price": 1000.0,
      "last_price": 1000.0,
      "best_price": 1000.0,
      "worst_price": 1000.0,
      "score": 73,
      "change_rate_at_signal": 2.56,
      "volume_ratio_at_signal": 0.72,
      "alert": null,
      "results": {
        "latest_pct": 0.0,
        "max_gain": 0.0,
        "max_drawdown": 0.0
      },
      "age_minutes": 0.89
    },
    {
      "key": "ai_pool:2454:71:4545.0",
      "module": "ai_pool",
      "reason": "api_ai_pool",
      "created_at": "2026-06-03T06:05:54.507913+00:00",
      "updated_at": "2026-06-03T06:06:49.521840+00:00",
      "status": "open",
      "code": "2454",
      "name": "聯發科",
      "sector": "半導體",
      "entry_price": 4545.0,
      "last_price": 4545.0,
      "best_price": 4545.0,
      "worst_price": 4545.0,
      "score": 71,
      "change_rate_at_signal": 0.44,
      "volume_ratio_at_signal": 0.67,
      "alert": null,
      "results": {
        "latest_pct": 0.0,
        "max_gain": 0.0,
        "max_drawdown": 0.0
      },
      "age_minutes": 0.92
    },
    {
      "key": "ai_pool:3443:59:4605.0",
      "module": "ai_pool",
      "reason": "api_ai_pool",
      "created_at": "2026-06-03T06:05:54.507922+00:00",
      "updated_at": "2026-06-03T06:06:50.865169+00:00",
      "status": "open",
      "code": "3443",
      "name": "創意",
      "sector": "半導體",
      "entry_price": 4605.0,
      "last_price": 4605.0,
      "best_price": 4605.0,
      "worst_price": 4605.0,
      "score": 59,
      "change_rate_at_signal": 1.54,
      "volume_ratio_at_signal": 0.57,
      "alert": null,
      "results": {
        "latest_pct": 0.0,
        "max_gain": 0.0,
        "max_drawdown": 0.0
      },
      "age_minutes": 0.94
    },
    {
      "key": "ai_pool:2382:58:417.0",
      "module": "ai_pool",
      "reason": "api_ai_pool",
      "created_at": "2026-06-03T06:05:54.507934+00:00",
      "updated_at": "2026-06-03T06:06:52.526123+00:00",
      "status": "open",
      "code": "2382",
      "name": "廣達",
      "sector": "AI伺服器",
      "entry_price": 417.0,
      "last_price": 417.0,
      "best_price": 417.0,
      "worst_price": 417.0,
      "score": 58,
      "change_rate_at_signal": 4.11,
      "volume_ratio_at_signal": 0.72,
      "alert": null,
      "results": {
        "latest_pct": 0.0,
        "max_gain": 0.0,
        "max_drawdown": 0.0
      },
      "age_minutes": 0.97
    },
    {
      "key": "ai_pool:3017:57:2855.0",
      "module": "ai_pool",
      "reason": "api_ai_pool",
      "created_at": "2026-06-03T06:05:54.507944+00:00",
      "updated_at": "2026-06-03T06:06:54.300808+00:00",
      "status": "open",
      "code": "3017",
      "name": "奇鋐",
      "sector": "AI散熱",
      "entry_price": 2855.0,
      "last_price": 2855.0,
      "best_price": 2855.0,
      "worst_price": 2855.0,
      "score": 57,
      "change_rate_at_signal": 5.74,
      "volume_ratio_at_signal": 1.64,
      "alert": null,
      "results": {
        "latest_pct": 0.0,
        "max_gain": 0.0,
        "max_drawdown": 0.0
      },
      "age_minutes": 1.0
    },
    {
      "key": "ai_pool:2356:50:85.4",
      "module": "ai_pool",
      "reason": "api_ai_pool",
      "created_at": "2026-06-03T06:05:54.507953+00:00",
      "updated_at": "2026-06-03T06:06:55.720532+00:00",
      "status": "open",
      "code": "2356",
      "name": "英業達",
      "sector": "電腦週邊",
      "entry_price": 85.4,
      "last_price": 85.4,
      "best_price": 85.4,
      "worst_price": 85.4,
      "score": 50,
      "change_rate_at_signal": 5.95,
      "volume_ratio_at_signal": 0.67,
      "alert": null,
      "results": {
        "latest_pct": 0.0,
        "max_gain": 0.0,
        "max_drawdown": 0.0
      },
      "age_minutes": 1.02
    },
    {
      "key": "ai_pool:2368:48:1385.0",
      "module": "ai_pool",
      "reason": "api_ai_pool",
      "created_at": "2026-06-03T06:05:54.507966+00:00",
      "updated_at": "2026-06-03T06:06:57.462974+00:00",
      "status": "open",
      "code": "2368",
      "name": "金像電",
      "sector": "PCB",
      "entry_price": 1385.0,
      "last_price": 1385.0,
      "best_price": 1385.0,
      "worst_price": 1385.0,
      "score": 48,
      "change_rate_at_signal": 8.62,
      "volume_ratio_at_signal": 1.02,
      "alert": null,
      "results": {
        "latest_pct": 0.0,
        "max_gain": 0.0,
        "max_drawdown": 0.0
      },
      "age_minutes": 1.05
    },
    {
      "key": "ai_pool:3711:40:618.0",
      "module": "ai_pool",
      "reason": "api_ai_pool",
      "created_at": "2026-06-03T06:05:54.507980+00:00",
      "updated_at": "2026-06-03T06:06:59.172115+00:00",
      "status": "open",
      "code": "3711",
      "name": "日月光投控",
      "sector": "半導體",
      "entry_price": 618.0,
      "last_price": 618.0,
      "best_price": 618.0,
      "worst_price": 618.0,
      "score": 40,
      "change_rate_at_signal": 4.74,
      "volume_ratio_at_signal": 1.08,
      "alert": null,
      "results": {
        "latest_pct": 0.0,
        "max_gain": 0.0,
        "max_drawdown": 0.0
      },
      "age_minutes": 1.08
    },
    {
      "key": "fund_flow:1513:100:184.5",
      "module": "fund_flow",
      "reason": "api_fund_flow",
      "created_at": "2026-06-03T06:06:02.264588+00:00",
      "updated_at": "2026-06-03T11:22:17.988054+00:00",
      "status": "closed",
      "code": "1513",
      "name": "中興電",
      "sector": "重電",
      "entry_price": 184.5,
      "last_price": 184.5,
      "best_price": 184.5,
      "worst_price": 184.5,
      "score": 100,
      "change_rate_at_signal": 9.82,
      "volume_ratio_at_signal": 5.28,
      "alert": "隔日沖風險警報",
      "results": {
        "latest_pct": 0.0,
        "max_gain": 0.0,
        "max_drawdown": 0.0,
        "pct_5m": 0.0,
        "pct_10m": 0.0,
        "pct_30m": 0.0,
        "pct_close_proxy": 0.0
      },
      "age_minutes": 316.26
    },
    {
      "key": "fund_flow:1514:100:136.0",
      "module": "fund_flow",
      "reason": "api_fund_flow",
      "created_at": "2026-06-03T06:06:02.264614+00:00",
      "updated_at": "2026-06-03T11:22:19.699965+00:00",
      "status": "closed",
      "code": "1514",
      "name": "亞力",
      "sector": "重電",
      "entry_price": 136.0,
      "last_price": 136.0,
      "best_price": 136.0,
      "worst_price": 136.0,
      "score": 100,
      "change_rate_at_signal": 9.67,
      "volume_ratio_at_signal": 4.86,
      "alert": "隔日沖風險警報",
      "results": {
        "latest_pct": 0.0,
        "max_gain": 0.0,
        "max_drawdown": 0.0,
        "pct_5m": 0.0,
        "pct_10m": 0.0,
        "pct_30m": 0.0,
        "pct_close_proxy": 0.0
      },
      "age_minutes": 316.29
    },
    {
      "key": "fund_flow:1609:100:42.15",
      "module": "fund_flow",
      "reason": "api_fund_flow",
      "created_at": "2026-06-03T06:06:02.264622+00:00",
      "updated_at": "2026-06-03T11:22:21.367524+00:00",
      "status": "closed",
      "code": "1609",
      "name": "大亞",
      "sector": "電線電纜",
      "entry_price": 42.15,
      "last_price": 42.15,
      "best_price": 42.15,
      "worst_price": 42.15,
      "score": 100,
      "change_rate_at_signal": 9.9,
      "volume_ratio_at_signal": 2.94,
      "alert": "隔日沖風險警報",
      "results": {
        "latest_pct": 0.0,
        "max_gain": 0.0,
        "max_drawdown": 0.0,
        "pct_5m": 0.0,
        "pct_10m": 0.0,
        "pct_30m": 0.0,
        "pct_close_proxy": 0.0
      },
      "age_minutes": 316.32
    },
    {
      "key": "fund_flow:1605:92:42.7",
      "module": "fund_flow",
      "reason": "api_fund_flow",
      "created_at": "2026-06-03T06:06:02.264630+00:00",
      "updated_at": "2026-06-03T11:22:23.195196+00:00",
      "status": "closed",
      "code": "1605",
      "name": "華新",
      "sector": "電線電纜",
      "entry_price": 42.7,
      "last_price": 42.7,
      "best_price": 42.7,
      "worst_price": 42.7,
      "score": 92,
      "change_rate_at_signal": 5.56,
      "volume_ratio_at_signal": 1.81,
      "alert": "大戶進場警報",
      "results": {
        "latest_pct": 0.0,
        "max_gain": 0.0,
        "max_drawdown": 0.0,
        "pct_5m": 0.0,
        "pct_10m": 0.0,
        "pct_30m": 0.0,
        "pct_close_proxy": 0.0
      },
      "age_minutes": 316.35
    },
    {
      "key": "fund_flow:3324:100:1280.0",
      "module": "fund_flow",
      "reason": "api_fund_flow",
      "created_at": "2026-06-03T06:06:02.264637+00:00",
      "updated_at": "2026-06-03T11:22:24.835780+00:00",
      "status": "closed",
      "code": "3324",
      "name": "雙鴻",
      "sector": "AI散熱",
      "entry_price": 1280.0,
      "last_price": 1280.0,
      "best_price": 1280.0,
      "worst_price": 1280.0,
      "score": 100,
      "change_rate_at_signal": 9.87,
      "volume_ratio_at_signal": 1.26,
      "alert": "大戶進場警報",
      "results": {
        "latest_pct": 0.0,
        "max_gain": 0.0,
        "max_drawdown": 0.0,
        "pct_5m": 0.0,
        "pct_10m": 0.0,
        "pct_30m": 0.0,
        "pct_close_proxy": 0.0
      },
      "age_minutes": 316.38
    },
    {
      "key": "fund_flow:8046:87:904.0",
      "module": "fund_flow",
      "reason": "api_fund_flow",
      "created_at": "2026-06-03T06:06:02.264644+00:00",
      "updated_at": "2026-06-03T11:22:26.684889+00:00",
      "status": "closed",
      "code": "8046",
      "name": "南電",
      "sector": "半導體",
      "entry_price": 904.0,
      "last_price": 904.0,
      "best_price": 904.0,
      "worst_price": 904.0,
      "score": 87,
      "change_rate_at_signal": 4.87,
      "volume_ratio_at_signal": 1.22,
      "alert": "大戶進場警報",
      "results": {
        "latest_pct": 0.0,
        "max_gain": 0.0,
        "max_drawdown": 0.0,
        "pct_5m": 0.0,
        "pct_10m": 0.0,
        "pct_30m": 0.0,
        "pct_close_proxy": 0.0
      },
      "age_minutes": 316.41
    },
    {
      "key": "fund_flow:2409:100:28.75",
      "module": "fund_flow",
      "reason": "api_fund_flow",
      "created_at": "2026-06-03T06:06:02.264651+00:00",
      "updated_at": "2026-06-03T11:22:29.360887+00:00",
      "status": "closed",
      "code": "2409",
      "name": "友達",
      "sector": "面板",
      "entry_price": 28.75,
      "last_price": 28.75,
      "best_price": 28.75,
      "worst_price": 28.75,
      "score": 100,
      "change_rate_at_signal": 9.94,
      "volume_ratio_at_signal": 0.98,
      "alert": "大戶進場警報",
      "results": {
        "latest_pct": 0.0,
        "max_gain": 0.0,
        "max_drawdown": 0.0,
        "pct_5m": 0.0,
        "pct_10m": 0.0,
        "pct_30m": 0.0,
        "pct_close_proxy": 0.0
      },
      "age_minutes": 316.45
    },
    {
      "key": "fund_flow:2324:91:47.05",
      "module": "fund_flow",
      "reason": "api_fund_flow",
      "created_at": "2026-06-03T06:06:02.264658+00:00",
      "updated_at": "2026-06-03T11:22:32.942830+00:00",
      "status": "closed",
      "code": "2324",
      "name": "仁寶",
      "sector": "電腦週邊",
      "entry_price": 47.05,
      "last_price": 47.05,
      "best_price": 47.05,
      "worst_price": 47.05,
      "score": 91,
      "change_rate_at_signal": 6.08,
      "volume_ratio_at_signal": 2.24,
      "alert": "隔日沖風險警報",
      "results": {
        "latest_pct": 0.0,
        "max_gain": 0.0,
        "max_drawdown": 0.0,
        "pct_5m": 0.0,
        "pct_10m": 0.0,
        "pct_30m": 0.0,
        "pct_close_proxy": 0.0
      },
      "age_minutes": 316.51
    },
    {
      "key": "fund_flow:3711:51:618.0",
      "module": "fund_flow",
      "reason": "api_fund_flow",
      "created_at": "2026-06-03T06:06:02.264665+00:00",
      "updated_at": "2026-06-03T06:06:59.172133+00:00",
      "status": "open",
      "code": "3711",
      "name": "日月光投控",
      "sector": "半導體",
      "entry_price": 618.0,
      "last_price": 618.0,
      "best_price": 618.0,
      "worst_price": 618.0,
      "score": 51,
      "change_rate_at_signal": 4.74,
      "volume_ratio_at_signal": 1.08,
      "alert": "隔日沖風險警報",
      "results": {
        "latest_pct": 0.0,
        "max_gain": 0.0,
        "max_drawdown": 0.0
      },
      "age_minutes": 0.95
    },
    {
      "key": "fund_flow:2379:30:646.0",
      "module": "fund_flow",
      "reason": "api_fund_flow",
      "created_at": "2026-06-03T06:06:02.264675+00:00",
      "updated_at": "2026-06-03T06:07:00.922388+00:00",
      "status": "open",
      "code": "2379",
      "name": "瑞昱",
      "sector": "半導體",
      "entry_price": 646.0,
      "last_price": 646.0,
      "best_price": 646.0,
      "worst_price": 646.0,
      "score": 30,
      "change_rate_at_signal": -1.07,
      "volume_ratio_at_signal": 0.87,
      "alert": "資金退潮警報",
      "results": {
        "latest_pct": 0.0,
        "max_gain": 0.0,
        "max_drawdown": 0.0
      },
      "age_minutes": 0.98
    }
  ]
}